pipuptodate/LICENSE
pipuptodate/README.MD
pipuptodate/__init__.py
pipuptodate/requirements.txt
pipuptodate/thirdparty.json
pipuptodate-0.10.dist-info/LICENSE.rst
pipuptodate-0.10.dist-info/METADATA
pipuptodate-0.10.dist-info/WHEEL
pipuptodate-0.10.dist-info/top_level.txt
pipuptodate-0.10.dist-info/RECORD
